Metadata-Version: 2.1
Name: mongoudaan
Version: 0.0.1
Summary: mongodb file storing
Author: Sahil Apte
Author-email: sahilapte1@gmail.com
Keywords: store files,database,store,file,sahil,mongo
Classifier: Development Status :: 1 - Planning
Classifier: Intended Audience :: Developers
Classifier: Programming Language :: Python :: 3
Classifier: Operating System :: Unix
Classifier: Operating System :: MacOS :: MacOS X
Classifier: Operating System :: Microsoft :: Windows
License-File: LICENCE
